MANIFEST.in
README.md
astc_codec.cpp
astc_codec.h
astc_codec.pxd
astc_codec.pyx
setup.cfg
setup.py
astc-codec/src/decoder/astc_file.cc
astc-codec/src/decoder/codec.cc
astc-codec/src/decoder/endpoint_codec.cc
astc-codec/src/decoder/footprint.cc
astc-codec/src/decoder/integer_sequence_codec.cc
astc-codec/src/decoder/intermediate_astc_block.cc
astc-codec/src/decoder/logical_astc_block.cc
astc-codec/src/decoder/partition.cc
astc-codec/src/decoder/physical_astc_block.cc
astc-codec/src/decoder/quantization.cc
astc-codec/src/decoder/weight_infill.cc
astc-codec/src/decoder/tools/astc_inspector_cli.cc
astc_codec.egg-info/PKG-INFO
astc_codec.egg-info/SOURCES.txt
astc_codec.egg-info/dependency_links.txt
astc_codec.egg-info/top_level.txt